tgx/__init__.py
tgx/classes/__init__.py
tgx/classes/graph.py
tgx/data/__init__.py
tgx/data/builtin.py
tgx/data/tgb.py
tgx/io/__init__.py
tgx/io/read.py
tgx/io/write.py
tgx/utils/__init__.py
tgx/utils/graph_utils.py
tgx/utils/plotting_utils.py
tgx/utils/stat.py
tgx/viz/TEA.py
tgx/viz/TET.py
tgx/viz/__init__.py
py_tgx-0.3.1.dist-info/LICENSE
py_tgx-0.3.1.dist-info/METADATA
py_tgx-0.3.1.dist-info/WHEEL
py_tgx-0.3.1.dist-info/top_level.txt
py_tgx-0.3.1.dist-info/RECORD
