Metadata-Version: 2.1
Name: py-tgx
Version: 0.3.1
Summary: Temporal Graph Visualization with TGX
Home-page: https://github.com/ComplexData-MILA/TGX
Author: ["Razieh Shirzadkhani <razieh.shirzadkhani@gmail.com>", "shenyang Huang <shenyang.huang@mail.mcgill.ca>", "Elahe Kooshafar", "Farimah Poursafaei"]
Author-email: razieh.shirzadkhani@gmail.com
License: MIT
Project-URL: Bug Tracker, https://github.com/fpour/TGX/issues
Keywords: Temporal Graph Visualization
Classifier: Programming Language :: Python :: 3.9
Requires-Python: >=3.6
License-File: LICENSE
Requires-Dist: appdirs
Requires-Dist: networkx
Requires-Dist: numpy
Requires-Dist: pandas
Requires-Dist: py-tgb
Requires-Dist: requests
Requires-Dist: scikit-learn
Requires-Dist: scipy
Requires-Dist: seaborn
Requires-Dist: sklearn
Requires-Dist: torch
Requires-Dist: torch-geometric-temporal
Requires-Dist: torch-geometric
Requires-Dist: torch-scatter
Requires-Dist: torch-sparse
Requires-Dist: tqdm
Requires-Dist: wandb
